django_easy_api/__init__.py
django_easy_api/asgi.py
django_easy_api/settings.py
django_easy_api/urls.py
django_easy_api/wsgi.py
easy_api/__init__.py
easy_api/admin.py
easy_api/api.py
easy_api/apps.py
easy_api/models.py
easy_api/tests.py
easy_api/views.py
django_model_api-1.4.dist-info/METADATA
django_model_api-1.4.dist-info/WHEEL
django_model_api-1.4.dist-info/top_level.txt
django_model_api-1.4.dist-info/RECORD
