Metadata-Version: 2.1
Name: django-model-api
Version: 1.4
Summary: Create model based api without any extra code.
Home-page: https://github.com/kumar-sanchay/django-easy-api
Author: Sanchay Kumar
Author-email: dsanchaykumar@gmail.com
License: MIT
Platform: UNKNOWN
Requires-Dist: django
Requires-Dist: django-filter
Requires-Dist: djangorestframework
Requires-Dist: markdown
